{
  "reviews": [
    {
      "tags": ["#리엑트"],
      "tag": "<span class=\"colorful-text\">#리엑트 </span>리엑트를 하다가 생긴 어려운 점들",
      "title": "리엑트를 하다가 생긴 어려운 점들",
      "problem": "리엑트를 하다가 생긴 어려운 점들",
      "question": "리엑트를 하다가 생긴 어려운 점들\n리엑트를 하다가 생긴 어려운 점들\n리엑트를 하다가 생긴 어려운 점들",
      "code": "",
      "id": 1
    },
    {
      "tags": ["#자바스크립트", "#재밌다"],
      "tag": "<span class=\"colorful-text\">#자바스크립트 </span><span class=\"colorful-text\">#재밌다 </span>자바스크립트를 사랑해주세요!!",
      "title": "자바스크립트를 사랑해주세요!!asdfasfsdfsdfssafsafasfasdfadsfasfsdfsadfa",
      "problem": "자바스크립트를 사랑해주세요!!!!!!",
      "question": "자바스크립트를 사랑해주세요!!!!!!",
      "code": "<span class = \"hg-var-code\">const</span> a = <span class = \"hg-num-code\">3</span>;\n<span class = \"hg-var-code\">const</span> b = <span class = \"hg-num-code\">3</span>;\n<span class = \"hg-var-code\">const</span> c = <span class = \"hg-num-code\">3</span>;\n<span class = \"hg-var-code\">const</span> d = <span class = \"hg-num-code\">3</span>;\n<span class = \"hg-var-code\">const</span> e = <span class = \"hg-num-code\">3</span>;\n<span class = \"hg-var-code\">const</span> f = <span class = \"hg-num-code\">3</span>;\n<span class = \"hg-var-code\">const</span> g = <span class = \"hg-num-code\">3</span>;\n<span class = \"hg-var-code\">const</span> h = <span class = \"hg-num-code\">3</span>;\n<span class = \"hg-var-code\">const</span> k = <span class = \"hg-num-code\">3</span>;",
      "id": 4
    },
    {
      "tags": ["#자바스크립트", "#재밌다"],
      "tag": "<span class=\"colorful-text\">#자바스크립트 </span><span class=\"colorful-text\">#재밌다 </span>자바스크립트를 사랑해주세요!!",
      "title": "자바스크립트를 사랑해주세요!!",
      "problem": "자바스크립트를 사랑해주세요!!!!!!",
      "question": "자바스크립트를 사랑해주세요!!!!!!",
      "code": "<span class = \"hg-var-code\">const</span> a = <span class = \"hg-num-code\">3</span>;\n<span class = \"hg-var-code\">const</span> b = <span class = \"hg-num-code\">3</span>;\n<span class = \"hg-var-code\">const</span> c = <span class = \"hg-num-code\">3</span>;\n<span class = \"hg-var-code\">const</span> d = <span class = \"hg-num-code\">3</span>;\n<span class = \"hg-var-code\">const</span> e = <span class = \"hg-num-code\">3</span>;\n<span class = \"hg-var-code\">const</span> f = <span class = \"hg-num-code\">3</span>;\n<span class = \"hg-var-code\">const</span> g = <span class = \"hg-num-code\">3</span>;\n<span class = \"hg-var-code\">const</span> h = <span class = \"hg-num-code\">3</span>;\n<span class = \"hg-var-code\">const</span> k = <span class = \"hg-num-code\">3</span>;",
      "id": 5
    },
    {
      "tags": ["#리엑트", "#재밌다", "#우와"],
      "tag": "<span class=\"colorful-text\">#리엑트 </span><span class=\"colorful-text\">#재밌다 </span><span class=\"colorful-text\">#우와 </span>리엑트 정말 재밌다.",
      "title": "리엑트 정말 재밌다.",
      "problem": "리엑트 정말 재밌다.\n리엑트 정말 재밌다.\n리엑트 정말 재밌다.\n리엑트 정말 재밌다.\n리엑트 정말 재밌다.",
      "question": "리엑트 정말 재밌다.\n리엑트 정말 재밌다.\n리엑트 정말 재밌다.\n리엑트 정말 재밌다.\n리엑트 정말 재밌다.\n",
      "code": "<span class=\"hg-function-keyword-code\">function</span> <span class = \"hg-word-code\">solution<span class = \"hg-word-parenthesis-code\"><span class = \"hg-parenthesis-code\">(</span><span class = \"hg-fc-parenthesis-code\">n</span><span class = \"hg-parenthesis-code\">)</span></span></span> <span class = \"hg-brace-code\">{</span>\n    <span class=\"hg-var-code\">let</span> answer = <span class=\"hg-num-code\">0</span>;\n    \n    <span class = \"hg-word-code\"><span class=\"hg-block-code\">while</span><span class = \"hg-word-parenthesis-code\"><span class = \"hg-parenthesis-code\">(</span>n <span data-testid = \"hg-code-last\" class=\"hg-hyper-code\">&gt;</span> <span class=\"hg-num-code\">0</span><span class = \"hg-parenthesis-code\">)</span></span></span> <span class = \"hg-brace-code\">{</span>\n        <span class = \"hg-word-code\"><span class=\"hg-conditional-code\">if</span><span class = \"hg-word-parenthesis-code\"><span class = \"hg-parenthesis-code\">(</span>n % <span class=\"hg-num-code\">2</span> === <span class=\"hg-num-code\">1</span><span class = \"hg-parenthesis-code\">)</span></span></span> <span class = \"hg-brace-code\">{</span>\n            n -= <span class=\"hg-num-code\">1</span>;\n            answer += <span class=\"hg-num-code\">1</span>\n        <span class = \"hg-brace-code\">}</span>\n        n /= <span class=\"hg-num-code\">2</span>;\n    <span class = \"hg-brace-code\">}</span>\n\n    <span class=\"hg-return-code\">return</span> answer;\n<span class = \"hg-brace-code\">}</span>",
      "id": 6
    }
  ]
}
